Facebooker/data_type.py
Facebooker/facebook.py
Facebooker/like_action.py
Facebooker/privacy_level.py
Facebooker/version.py
Facebooker-1.3.1.dist-info/LICENSE
Facebooker-1.3.1.dist-info/METADATA
Facebooker-1.3.1.dist-info/WHEEL
Facebooker-1.3.1.dist-info/top_level.txt
Facebooker-1.3.1.dist-info/RECORD
