Metadata-Version: 2.1
Name: Facebooker
Version: 1.3.1
Summary: An un official facebook api
Home-page: https://github.com/gpwork4u/Facebooker
Author: gpwork4u
Author-email: gpwork4u@gmail.com
License: UNKNOWN
Platform: UNKNOWN
Classifier: Programming Language :: Python :: 3
Classifier: License :: OSI Approved :: MIT License
Classifier: Operating System :: OS Independent
Requires-Python: >=3.6
Requires-Dist: lxml
Requires-Dist: beautifulsoup4
Requires-Dist: requests
Requires-Dist: requests-toolbelt
